pprl_core/__init__.py
pprl_core/bits.py
pprl_core/common.py
pprl_core/harden.py
pprl_core/phonetics_extra.py
pprl_core/similarity.py
pprl_core/transform.py
pprl_core-0.1.4.dist-info/LICENSE
pprl_core-0.1.4.dist-info/METADATA
pprl_core-0.1.4.dist-info/WHEEL
pprl_core-0.1.4.dist-info/RECORD
