Metadata-Version: 2.3
Name: pprl-core
Version: 0.1.4
Summary: Facilities for performing privacy-preserving record linkage with Bloom filters.
License: MIT
Keywords: record linkage,privacy,bloom filter,bitarray,cryptography
Author: Maximilian Jugl
Author-email: Maximilian.Jugl@medizin.uni-leipzig.de
Requires-Python: >=3.10
Classifier: Development Status :: 4 - Beta
Classifier: Intended Audience :: Developers
Classifier: Intended Audience :: Information Technology
Classifier: Intended Audience :: Science/Research
Classifier: Topic :: Scientific/Engineering
Classifier: Topic :: Software Development :: Libraries :: Python Modules
Requires-Dist: bitarray (>=3.0.0,<4)
Requires-Dist: pyphonetics (>=0.5.0,<1)
Requires-Dist: unidecode (>=1.3.0,<2)
Project-URL: Repository, https://github.com/mjugl/pprl-core
